PySensors3-0.1.0.dist-info/DESCRIPTION.rst
PySensors3-0.1.0.dist-info/METADATA
PySensors3-0.1.0.dist-info/RECORD
PySensors3-0.1.0.dist-info/WHEEL
PySensors3-0.1.0.dist-info/metadata.json
PySensors3-0.1.0.dist-info/top_level.txt
sensors/__init__.py
sensors/cli.py
sensors/stdc.py
