Metadata-Version: 2.0
Name: PySensors3
Version: 0.1.0
Summary: Python3 bindings to libsensors (via ctypes)
Home-page: http://pypi.python.org/pypi/PySensors3/
Author: Richard Hull
Author-email: richard.hull@destructuring-bind.org
License: LGPL v2.1
Keywords: sensors,hardware,monitoring
Platform: UNKNOWN
Classifier: Development Status :: 3 - Alpha
Classifier: Intended Audience :: Developers
Classifier: License :: OSI Approved
Classifier: License :: OSI Approved :: GNU Lesser General Public License v2 or later (LGPLv2+)
Classifier: Operating System :: POSIX :: Linux
Classifier: Programming Language :: Python
Classifier: Programming Language :: Python :: 2
Classifier: Programming Language :: Python :: 2.6
Classifier: Programming Language :: Python :: 2.7
Classifier: Programming Language :: Python :: 3.3
Classifier: Programming Language :: Python :: 3.4
Classifier: Programming Language :: Python :: 3.5
Classifier: Programming Language :: Python :: 3.6
Classifier: Programming Language :: Python :: 3.7
Classifier: Programming Language :: Python :: Implementation
Classifier: Programming Language :: Python :: Implementation :: CPython
Classifier: Programming Language :: Python :: Implementation :: PyPy
Classifier: Topic :: System
Classifier: Topic :: System :: Hardware
Classifier: Topic :: System :: Monitoring
